{
  "$schema": "http://json-schema.org/draft-07/schema#",
  "$id": "http://tmi-platform.org/schemas/shared/primitives.schema.json",

  "definitions": {

    "uei": {"$ref": "http://minimi.org/schemas/fields.json#/definitions/uei"},

    "name": {
      "title": "Name",
      "type": "string",
      "pattern": "^(\\s?\\S+\\s?){1,20}$",
      "errorMessage": "should only be 1 to 20 words"
    },

    "description": {
      "title": "Description",
      "type": "string",
      "pattern": "^(\\s?\\S+\\s?){0,500}$",
      "errorMessage": "should only be up to 500 words"
    },

    "exposure": {
      "title": "Exposure",
      "type": "string",
      "enum": [
        "owner",
        "administrator",
        "moderator",
        "member",
        "visitor",
        "authenticated",
        "anonymous"
      ],
      "default": "owner"
    },

    "status": {
      "title": "Status",
      "type": "string",
      "enum": [
        "draft",
        "active",
        "retired",
        "suspended",
        "deleted"
      ],
      "default": "draft"
    },

    "entityType": {
      "type": "string",
      "enum": [
        "agreement",
        "collective",
        "profile",
        "schema",
        "post",
        "user"
      ]
    }
  }
}